fe_openedx_alerts/__init__.py
fe_openedx_alerts/es-status-not-ok.txt
fe_openedx_alerts/es-status-ok.txt
fe_openedx_alerts/es_status.py
fe_openedx_alerts-0.0.5.dist-info/LICENSE
fe_openedx_alerts-0.0.5.dist-info/METADATA
fe_openedx_alerts-0.0.5.dist-info/WHEEL
fe_openedx_alerts-0.0.5.dist-info/entry_points.txt
fe_openedx_alerts-0.0.5.dist-info/RECORD
