Metadata-Version: 2.1
Name: fe-openedx-alerts
Version: 0.0.5
Summary: 
Author: Fernando Espíndola
Author-email: fer.esp@gmail.com
Requires-Python: >=3.9,<4.0
Classifier: Programming Language :: Python :: 3
Classifier: Programming Language :: Python :: 3.9
Classifier: Programming Language :: Python :: 3.10
Classifier: Programming Language :: Python :: 3.11
Requires-Dist: requests (>=2.28.2,<3.0.0)
